pdfservices_sdk_foxit/__init__.py
pdfservices_sdk_foxit/pdf_service_sdk.py
pdfservices_sdk_foxit-1.0.0.dist-info/METADATA
pdfservices_sdk_foxit-1.0.0.dist-info/WHEEL
pdfservices_sdk_foxit-1.0.0.dist-info/licenses/LICENSE
pdfservices_sdk_foxit-1.0.0.dist-info/RECORD
