Metadata-Version: 2.4
Name: pdfservices_sdk_foxit
Version: 1.0.0
Summary: A SDK wrapper for Foxit's PDF Services and Document Generation APIs.
Project-URL: Homepage, https://github.com/foxitsoftware/pdfservicespythonsdk
Project-URL: Issues, https://github.com/foxitsoftware/pdfservicespythonsdk/issues
Author-email: Raymond Camden <jedimaster@foxitsoftware.com>
License: 
License-File: LICENSE
Classifier: Operating System :: OS Independent
Classifier: Programming Language :: Python :: 3
Requires-Python: >=3.9
